napari_ip_workflow/__init__.py
napari_ip_workflow/ipfunctions.py
napari_ip_workflow/napari.yaml
napari_ip_workflow/segwidget.py
napari_ip_workflow/_tests/__init__.py
napari_IP_workflow-0.0.3.dist-info/LICENSE
napari_IP_workflow-0.0.3.dist-info/METADATA
napari_IP_workflow-0.0.3.dist-info/WHEEL
napari_IP_workflow-0.0.3.dist-info/entry_points.txt
napari_IP_workflow-0.0.3.dist-info/top_level.txt
napari_IP_workflow-0.0.3.dist-info/RECORD
