Metadata-Version: 2.1
Name: napari-IP-workflow
Version: 0.0.3
Summary: A plugin to do image preprocessing, segmentation, and measurements on other images.
Home-page: https://github.com/jayunruh/napari-IP-workflow
Author: Jay Unruh
Author-email: jru@stowers.org
License: GPL-3.0-only
Project-URL: Bug Tracker, https://github.com/jayunruh/napari-IP-workflow/issues
Project-URL: Documentation, https://github.com/jayunruh/napari-IP-workflow#README.md
Project-URL: Source Code, https://github.com/jayunruh/napari-IP-workflow
Project-URL: User Support, https://github.com/jayunruh/napari-IP-workflow/issues
Classifier: Development Status :: 2 - Pre-Alpha
Classifier: Intended Audience :: Developers
Classifier: Framework :: napari
Classifier: Topic :: Software Development :: Testing
Classifier: Programming Language :: Python
Classifier: Programming Language :: Python :: 3
Classifier: Programming Language :: Python :: 3.8
Classifier: Programming Language :: Python :: 3.9
Classifier: Programming Language :: Python :: 3.10
Classifier: Operating System :: OS Independent
Classifier: License :: OSI Approved :: GNU General Public License v3 (GPLv3)
Requires-Python: >=3.8
License-File: LICENSE
Requires-Dist: numpy
Requires-Dist: magicgui
Requires-Dist: qtpy
Requires-Dist: pandas
Requires-Dist: skimage
Provides-Extra: testing
Requires-Dist: tox ; extra == 'testing'
Requires-Dist: pytest ; extra == 'testing'
Requires-Dist: pytest-cov ; extra == 'testing'
Requires-Dist: pytest-qt ; extra == 'testing'
Requires-Dist: napari ; extra == 'testing'
Requires-Dist: pyqt5 ; extra == 'testing'
